{
  "IfcAirTerminal": "Воздухораспределитель",
  "IfcAirTerminalBox": "Клапан воздушный",
  "IfcAirToAirHeatRecovery": "Теплоутилизатор",
  "IfcAlarm": "Сигнализация",
  "IfcAudioVisualAppliance": "Аудиовизуальное оборудование",
  "IfcBeam": "Балка",
  "IfcBuilding": "Здание",
  "IfcBuildingElementProxy": "Прокси-элемент",
  "IfcBuildingStorey": "Этаж",
  "IfcCableCarrierFitting": "Фитинг кабельного лотка",
  "IfcCableCarrierSegment": "Сегмент кабельного лотка",
  "IfcCableFitting": "Фитинг кабеля",
  "IfcCableSegment": "Сегмент кабеля",
  "IfcChiller": "Чиллер",
  "IfcChimney": "Дымоход",
  "IfcColumn": "Колонна",
  "IfcCommunicationsAppliance": "Коммуникационное устройство",
  "IfcController": "Контроллер",
  "IfcCovering": "Покрытие",
  "IfcCurtainWall": "Стеклянная стена",
  "IfcDamper": "Демпфер",
  "IfcDistributionChamberElement": "Камера распределительная",
  "IfcDistribitionSystem": "Система распределения",
  "IfcDoor": "Дверь",
  "IfcDuctFitting": "Фитинг воздуховода",
  "IfcDuctSegment": "Сегмент воздуховода",
  "IfcDuctSilencer": "Глушитель шума",
  "IfcElectricAppliance": "Электроприбор",
  "IfcElectricDistributionBoard": "Распределительный щит",
  "IfcElectricFlowStorageDevice": "Устройство хранения электроэнергии",
  "IfcElectricMotor": "Электродвигатель",
  "IfcElementAssembly": "Сборный элемент",
  "IfcFan": "Вентилятор",
  "IfcFilter": "Фильтр",
  "IfcFireSuppressionTerminal": "Огнетушитель",
  "IfcFlowController": "Контроллер системы",
  "IfcFlowFitting": "Фитинг трубопровода",
  "IfcFlowInstrument": "Прибор контроля",
  "IfcFlowMeter": "Счетчик расхода",
  "IfcFlowSegment": "Сегмент трубопровода",
  "IfcFlowStorageDevice": "Устройство хранения",
  "IfcFlowTerminal": "Терминал системы",
  "IfcFooting": "Фундамент",
  "IfcFurniture": "Мебель",
  "IfcHeatExchanger": "Теплообменник",
  "IfcJunctionBox": "Распределительная коробка",
  "IfcLightFixture": "Осветительный прибор",
  "IfcMechanicalFastener": "Крепеж",
  "IfcMember": "Стержневой элемент",
  "IfcOutlet": "Розетка",
  "IfcPile": "Свая",
  "IfcPipeFitting": "Фитинг трубы",
  "IfcPipeSegment": "Сегмент трубы",
  "IfcProject": "Проект",
  "IfcProtectiveDevice": "Защитное устройство",
  "IfcPump": "Насос",
  "IfcRailing": "Ограждение",
  "IfcRamp": "Пандус",
  "IfcRampFlight": "Марш пандуса",
  "IfcRoof": "Крыша",
  "IfcSanitaryTerminal": "Санитарный прибор",
  "IfcSensor": "Датчик",
  "IfcSite": "Площадка",
  "IfcSlab": "Перекрытие",
  "IfcSpace": "Помещение",
  "IfcSpaceHeater": "Обогреватель",
  "IfcStackTerminal": "Вентиляционный терминал",
  "IfcStair": "Лестница",
  "IfcStairFlight": "Марш лестницы",
  "IfcSwitchingDevice": "Коммутационное устройство",
  "IfcSystem": "Система",
  "IfcTank": "Емкость",
  "IfcTransformer": "Трансформатор",
  "IfcUnitaryEquipment": "Единое оборудование",
  "IfcValve": "Клапан",
  "IfcWall": "Стена",
  "IfcWallElementedCase": "Составная стена",
  "IfcWallStandardCase": "Стандартная стена",
  "IfcWasteTerminal": "Сливной прибор",
  "IfcWindow": "Окно",
  "IfcZone": "Зона"
}